cloud-temp/__init__.py
cloud-temp/index.py
cloud-temp/main-pg.py
donutdb/__init__.py
donutdb/api/__init__.py
donutdb/api/console.py
donutdb/api/index.py
donutdb/api/local.py
donutdb/db/__init__.py
donutdb/db/index/__init__.py
donutdb/db/index/hnswlib.py
donutdb/db/postgres/db.py
donutdb/db/postgres/queries.py
donutdb/db/postgres/query_builder.py
donutdb/db/sqlite/__init__.py
donutdb/db/sqlite/db.py
donutdb/db/sqlite/queries.py
donutdb/db/sqlite/query_builder.py
donutdb/embedding/__init__.py
donutdb/embedding/openai.py
donutdb/embedding/utils.py
donutdb/utils/__init__.py
donutdb/utils/types.py
donutdb/utils/utils.py
donutdb-0.1.0.dist-info/LICENSE
donutdb-0.1.0.dist-info/METADATA
donutdb-0.1.0.dist-info/WHEEL
donutdb-0.1.0.dist-info/top_level.txt
donutdb-0.1.0.dist-info/RECORD
